vulseek/cli/main.py
vulseek-0.0.6.dist-info/METADATA
vulseek-0.0.6.dist-info/WHEEL
vulseek-0.0.6.dist-info/entry_points.txt
vulseek-0.0.6.dist-info/top_level.txt
vulseek-0.0.6.dist-info/RECORD
