Metadata-Version: 2.1
Name: vulseek
Version: 0.0.6
Summary: Vulseek Command Line Interface
Home-page: https://gitlab.com/securetia/vulseek/cli
Author: Fabian Martinez Portantier
Author-email: fportantier@securetia.com
License: BSD 3-clause
Keywords: security
Platform: UNKNOWN
Classifier: Environment :: Console
Classifier: Intended Audience :: Developers
Classifier: Intended Audience :: Information Technology
Classifier: Intended Audience :: System Administrators
Classifier: License :: OSI Approved :: BSD License
Classifier: Topic :: Security
Classifier: Topic :: System :: Networking
Classifier: Programming Language :: Python :: 3.0
Classifier: Programming Language :: Python :: 3.8
Requires-Dist: click
Requires-Dist: requests
Requires-Dist: requests-cache
